llm_privacy_filter/__init__.py
llm_privacy_filter/__main__.py
llm_privacy_filter/core.py
llm_privacy_filter/pdet.py
llm_privacy_filter/privacy_states.py
llm_privacy_filter/prompt_template.py
llm_privacy_filter/providers.py
llm_privacy_filter/utils.py
llm_privacy_filter-1.0.1.dist-info/licenses/LICENSE
llm_privacy_filter-1.0.1.dist-info/METADATA
llm_privacy_filter-1.0.1.dist-info/WHEEL
llm_privacy_filter-1.0.1.dist-info/top_level.txt
llm_privacy_filter-1.0.1.dist-info/RECORD
