Metadata-Version: 2.4
Name: llm-privacy-filter
Version: 1.0.1
Summary: A lightweight LLM-based privacy filter for masking sensitive entities in text.
Author-email: Okechukwu Obiahu <paulobiahu@gmail.com>
License: MIT
Project-URL: Repository, https://github.com/Data4i/llm_privacy_filter
Project-URL: Issues, https://github.com/Data4i/llm_privacy_filter/issues
Keywords: privacy,llm,masking,langchain,ai
Requires-Python: >=3.9
License-File: LICENSE
Requires-Dist: langchain>=0.3.27
Requires-Dist: langchain-ollama>=0.3.10
Provides-Extra: ollama
Requires-Dist: langchain-ollama>=0.3.10; extra == "ollama"
Provides-Extra: openai
Requires-Dist: langchain-openai>=0.3.35; extra == "openai"
Provides-Extra: anthropic
Requires-Dist: langchain-anthropic>=0.3.22; extra == "anthropic"
Provides-Extra: gemini
Requires-Dist: langchain-google-genai>=2.1.12; extra == "gemini"
Provides-Extra: all
Requires-Dist: langchain-ollama>=0.3.10; extra == "all"
Requires-Dist: langchain-openai>=0.3.35; extra == "all"
Requires-Dist: langchain-anthropic>=0.3.22; extra == "all"
Requires-Dist: langchain-google-genai>=2.1.12; extra == "all"
Dynamic: license-file
